{
  "seo": {
    "title": "Le Bouillon des Eaux Vives | Menu du jour",
    "description": "Menu du jour du restaurant Le Bouillon des Eaux Vives à Saint-Pierre-de-Bœuf."
  },
  "text": "Découvrez le menu du jour",
  "date": "2025-04-03T10:00:00",
  "starters": [
    {
      "name": "Salade de gésiers, croûton réduction balsamique",
      "description": ""
    }
  ],
  "additionalTextStarters": "",
  "mainDishes": [
    {
      "name": "Cuisse de poulet aux légumes, jus au romarin",
      "description": ""
    }
  ],
  "additionalTextMainDishes": "",
  "deserts": [
    {
      "name": "Fondant chocolat noir & chantilly",
      "description": ""
    }
  ],
  "additionalTextDeserts": "",
  "oneDishPrice": 14,
  "twoDishesPrice": 18,
  "threeDishesPrice": 22
}
