{
  "seo": {
    "title": "Le Bouillon des Eaux Vives | Menu du jour",
    "description": "Menu du jour du restaurant Le Bouillon des Eaux Vives à Saint-Pierre-de-Bœuf."
  },
  "text": "Découvrez le menu du jour",
  "date": "2024-08-28T10:00",
  "starters": [
    {
      "name": "Melon & Jambon cru",
      "description": ""
    }
  ],
  "additionalTextStarters": "",
  "mainDishes": [
    {
      "name": "Sauté d'agneau",
      "description": "accompagné de pennes à la tomate"
    }
  ],
  "additionalTextMainDishes": "",
  "deserts": [
    {
      "name": "Coupe Oreo",
      "description": "(Glace vanille, brisures d'Oreo & sauce chocolat)"
    }
  ],
  "additionalTextDeserts": "",
  "oneDishPrice": 14,
  "twoDishesPrice": 18,
  "threeDishesPrice": 22
}
